osmviz/__init__.py
osmviz/animation.py
osmviz/manager.py
osmviz-4.5.0.dist-info/METADATA
osmviz-4.5.0.dist-info/WHEEL
osmviz-4.5.0.dist-info/RECORD
