Metadata-Version: 2.4
Name: osmviz
Version: 4.5.0
Summary: OSMViz is a small set of Python tools for retrieving and using Mapnik tiles from a Slippy Map server (you may know these as OpenStreetMap images).
Project-URL: Changelog, https://github.com/hugovk/osmviz/releases
Project-URL: Documentation, https://hugovk.github.io/osmviz/
Project-URL: Homepage, https://github.com/hugovk/osmviz
Project-URL: Source, https://github.com/hugovk/osmviz
Author-email: Colin Bick and Contributors <colin.bick@gmail.com>
Maintainer: Hugo van Kemenade
License-Expression: MIT
Keywords: osm openstreetmap tiles visualization
Classifier: Intended Audience :: Developers
Classifier: Programming Language :: Python :: 3 :: Only
Classifier: Programming Language :: Python :: 3.9
Classifier: Programming Language :: Python :: 3.10
Classifier: Programming Language :: Python :: 3.11
Classifier: Programming Language :: Python :: 3.12
Classifier: Programming Language :: Python :: 3.13
Classifier: Programming Language :: Python :: 3.14
Classifier: Programming Language :: Python :: Implementation :: CPython
Classifier: Programming Language :: Python :: Implementation :: PyPy
Classifier: Topic :: Software Development :: Documentation
Requires-Python: >=3.9
Provides-Extra: tests
Requires-Dist: coverage; extra == 'tests'
Requires-Dist: pillow>=9.1; extra == 'tests'
Requires-Dist: pytest; extra == 'tests'
Requires-Dist: pytest-cov; extra == 'tests'
